[
  {
    "username": "sjames1958gm",
    "img": "https://avatars1.githubusercontent.com/u/4639625?v=4",
    "alltime": 8927,
    "recent": 35,
    "lastUpdate": "2018-05-29T14:07:27.314Z"
  },
  {
    "username": "Manish-Giri",
    "img": "https://avatars2.githubusercontent.com/u/11348778?v=4",
    "alltime": 6493,
    "recent": 2,
    "lastUpdate": "2018-05-27T17:55:40.981Z"
  },
  {
    "username": "anthonygallina1",
    "img": "https://avatars.githubusercontent.com/u/11003055?v=3",
    "alltime": 5530,
    "recent": 4,
    "lastUpdate": "2018-05-27T17:55:27.587Z"
  },
  {
    "username": "diomed",
    "img": "https://avatars3.githubusercontent.com/u/72777?v=3",
    "alltime": 5128,
    "recent": 1,
    "lastUpdate": "2018-05-27T14:54:59.952Z"
  },
  {
    "username": "Masd925",
    "img": "https://avatars.githubusercontent.com/u/9335367?v=3",
    "alltime": 4492,
    "recent": 13,
    "lastUpdate": "2018-05-27T17:55:10.628Z"
  }
]
